README.md
setup.py
acornio/__init__.py
acornio/acornio.py
acornio.egg-info/PKG-INFO
acornio.egg-info/SOURCES.txt
acornio.egg-info/dependency_links.txt
acornio.egg-info/top_level.txt