Metadata-Version: 2.1
Name: acornio
Version: 0.0.1
Summary: An asynchronous mail server
Home-page: https://github.com/joegasewicz/acorn-io
Author: Joe Gasewicz
Author-email: joegasewicz@gmail.com
License: UNKNOWN
Platform: UNKNOWN
Classifier: Programming Language :: Python :: 3
Classifier: Programming Language :: Python :: 3.7
Classifier: Programming Language :: Python :: 3.8
Classifier: Operating System :: OS Independent
